Workbook
Name aporte: Aplicativo!$D$16
Name dividendos_mensais: Aplicativo!$D$20
Name patrimonio: Aplicativo!$D$19
Name qtd_anos: Aplicativo!$D$17
Name rendimento_carteira: Aplicativo!$D$12
Name salario: Aplicativo!$D$11
Name sugestao_investimento: Aplicativo!$D$13
Name taxa_mensal: Aplicativo!$D$18

Sheet Aplicativo
B10: CONFIGURAÇÕES
B11: Salário | D11: 3000
B12: Rendimento da carteira | D12: 0.01
B13: Sugestão de investimento | D13: =salario*30% -> 900
B15: INVESTIMENTO MENSAL
B16: Quanto investir por mês? | D16: 600
B17: Por quantos anos vai investir? | D17: 5
B18: Qual é a taxa de rendimento mensal? | D18: 0.01079
B19: Patrimônio acumulado no período? | D19: =FV(taxa_mensal,qtd_anos*12,aporte*(-1)) -> 50266.148
B20: Dividendos mensais? | D20: =D19*rendimento_carteira -> 502.66148
B22: Cenários | D22: Dividendos
A23: 2 | B23: Patrimônio acumulado em 2 anos? | C23: =FV($D$18,$A23*12,$D$16*(-1)) -> 16336.576 | D23: =$C23*rendimento_carteira -> 163.36576
A24: 5 | B24: Patrimônio acumulado em 5 anos? | C24: =FV($D$18,$A24*12,$D$16*(-1)) -> 50266.148 | D24: =$C24*rendimento_carteira -> 502.66148
A25: 10 | B25: Patrimônio acumulado em 10 anos? | C25: =FV($D$18,$A25*12,$D$16*(-1)) -> 145970.53 | D25: =$C25*rendimento_carteira -> 1459.7053
A26: 20 | B26: Patrimônio acumulado em 20 anos? | C26: =FV($D$18,$A26*12,$D$16*(-1)) -> 675119.04 | D26: =$C26*rendimento_carteira -> 6751.1904
A27: 30 | B27: Patrimônio acumulado em 30 anos? | C27: =FV($D$18,$A27*12,$D$16*(-1)) -> 2593301.8 | D27: =$C27*rendimento_carteira -> 25933.018
B29: Perfil do investidor | C29: Conservador
B30: Valor a investir | C30: =aporte -> 600
B31: Valor sugerido | C31: =sugestao_investimento -> 900
B33: TIPO DE FII | C33: Percentual sugerido | D33: Valores
B34: PAPEL | C34: =VLOOKUP($C$29&"-"&$B34,Support_table!$A:$D,4,FALSE) -> 0.3 | D34: =$C$30*$C34 -> 180
B35: TIJOLO | C35: =VLOOKUP($C$29&"-"&$B35,Support_table!$A:$D,4,FALSE) -> 0.5 | D35: =$C$30*$C35 -> 300
B36: HÍBRIDO | C36: =VLOOKUP($C$29&"-"&$B36,Support_table!$A:$D,4,FALSE) -> 0.1 | D36: =$C$30*$C36 -> 60
B37: FOFs | C37: =VLOOKUP($C$29&"-"&$B37,Support_table!$A:$D,4,FALSE) -> 0.1 | D37: =$C$30*$C37 -> 60
B38: DESENVOLVIMENTO | C38: =VLOOKUP($C$29&"-"&$B38,Support_table!$A:$D,4,FALSE) -> 0 | D38: =$C$30*$C38 -> 0
B39: HOTELARIA | C39: =VLOOKUP($C$29&"-"&$B39,Support_table!$A:$D,4,FALSE) -> 0 | D39: =$C$30*$C39 -> 0
B40: Valor a investir | D40: =SUM(D34:D39) -> 600
B42: TIPO DE FII | C42: Percentual sugerido | D42: Valores
B43: PAPEL | C43: =VLOOKUP($C$29&"-"&$B43,Support_table!$A:$D,4,FALSE) -> 0.3 | D43: =sugestao_investimento*C43 -> 270
B44: TIJOLO | C44: =VLOOKUP($C$29&"-"&$B44,Support_table!$A:$D,4,FALSE) -> 0.5 | D44: =sugestao_investimento*C44 -> 450
B45: HÍBRIDO | C45: =VLOOKUP($C$29&"-"&$B45,Support_table!$A:$D,4,FALSE) -> 0.1 | D45: =sugestao_investimento*C45 -> 90
B46: FOFs | C46: =VLOOKUP($C$29&"-"&$B46,Support_table!$A:$D,4,FALSE) -> 0.1 | D46: =sugestao_investimento*C46 -> 90
B47: DESENVOLVIMENTO | C47: =VLOOKUP($C$29&"-"&$B47,Support_table!$A:$D,4,FALSE) -> 0 | D47: =sugestao_investimento*C47 -> 0
B48: HOTELARIA | C48: =VLOOKUP($C$29&"-"&$B48,Support_table!$A:$D,4,FALSE) -> 0 | D48: =sugestao_investimento*C48 -> 0
B49: Valor sugerido | D49: =SUM(D43:D48) -> 900

Sheet Support_table
A1: CHAVE | B1: PERFIL DE INVESTIDOR | C1: TIPO DE FII | D1: VALOR
A2: Conservador-PAPEL | B2: Consevador | C2: PAPEL | D2: 0.3 | H2: %
A3: Conservador-TIJOLO | B3: Consevador | C3: TIJOLO | D3: 0.5 | F3: Agressivo-PAPEL | H3: =VLOOKUP($F$3,$A:$D,4,FALSE) -> 0.5
A4: Conservador-HÍBRIDO | B4: Consevador | C4: HÍBRIDO | D4: 0.1
A5: Conservador-FOFs | B5: Consevador | C5: FOFs | D5: 0.1
A6: Conservador-DESENVOLVIMENTO | B6: Consevador | C6: DESENVOLVIMENTO | D6: 0
A7: Conservador-HOTELARIA | B7: Consevador | C7: HOTELARIA | D7: 0
A9: Moderado-PAPEL | B9: Moderado | C9: PAPEL | D9: 0.32
A10: Moderado-TIJOLO | B10: Moderado | C10: TIJOLO | D10: 0.35
A11: Moderado-HÍBRIDO | B11: Moderado | C11: HÍBRIDO | D11: 0.08
A12: Moderado-FOFs | B12: Moderado | C12: FOFs | D12: 0.05
A13: Moderado-DESENVOLVIMENTO | B13: Moderado | C13: DESENVOLVIMENTO | D13: 0.1
A14: Moderado-HOTELARIA | B14: Moderado | C14: HOTELARIA | D14: 0.1
A16: Agressivo-PAPEL | B16: Agressivo | C16: PAPEL | D16: 0.5
A17: Agressivo-TIJOLO | B17: Agressivo | C17: TIJOLO | D17: 0.1
... A21: Agressivo-HOTELARIA | B21: Agressivo | C21: HOTELARIA | D21: 0.1
